MANIFEST.in
README.md
requirements.txt
setup.cfg
setup.py
atlantiscli/__init__.py
atlantiscli/__main__.py
atlantiscli/apiclient.py
atlantiscli/atlantis.py
atlantiscli/cli.py
atlantiscli/config.py
atlantiscli.egg-info/PKG-INFO
atlantiscli.egg-info/SOURCES.txt
atlantiscli.egg-info/dependency_links.txt
atlantiscli.egg-info/entry_points.txt
atlantiscli.egg-info/not-zip-safe
atlantiscli.egg-info/requires.txt
atlantiscli.egg-info/top_level.txt