Metadata-Version: 1.1
Name: atlantiscli
Version: 0.0.5
Summary: An Atlantis CLI basic and commons modules
Home-page: https://github.com/spacetimelabs/atlantiscli
Author: Spacetime Labs
Author-email: lc@spacetimelabs.ai
License: BSD
Download-URL: https://github.com/spacetimelabs/atlantiscli/tarball/0.0.5
Platform: UNKNOWN
Classifier: Development Status :: 3 - Alpha
Classifier: Intended Audience :: Developers
Classifier: Programming Language :: Python :: 3
